[{"__symbolic":"module","version":3,"metadata":{"MentionListComponent":{"__symbolic":"class","decorators":[{"__symbolic":"call","expression":{"__symbolic":"reference","module":"@angular/core","name":"Component"},"arguments":[{"selector":"mention-list","styles":[".scrollable-menu {\n\t\t\tdisplay: block;\n\t\t\theight: auto;\n\t\t\tmax-height: 300px;\n\t\t\toverflow: auto;\n\t\t}","[hidden] {\n\t\t\tdisplay: none;\n\t\t}"],"template":"\n    <ul class=\"dropdown-menu scrollable-menu\" #list [hidden]=\"hidden\">\n\t\t\t\t<li *ngFor=\"let item of items; let i = index\" [class.active]=\"activeIndex==i\">\n\t\t\t\t\t\t<a class=\"text-primary\" (mousedown)=\"activeIndex=i;itemClick.emit();$event.preventDefault()\">\n\t\t\t\t\t\t\t<ng-template [ngTemplateOutlet]=\"listTemplate\" [ngOutletContext]=\"{'item': item}\"></ng-template>\n\t\t\t\t\t\t</a>\n        </li>\n    </ul>\n    "}]}],"members":{"list":[{"__symbolic":"property","decorators":[{"__symbolic":"call","expression":{"__symbolic":"reference","module":"@angular/core","name":"ViewChild"},"arguments":["list"]}]}],"itemClick":[{"__symbolic":"property","decorators":[{"__symbolic":"call","expression":{"__symbolic":"reference","module":"@angular/core","name":"Output"}}]}],"listTemplate":[{"__symbolic":"property","decorators":[{"__symbolic":"call","expression":{"__symbolic":"reference","module":"@angular/core","name":"Input"}}]}],"__ctor__":[{"__symbolic":"constructor","parameters":[{"__symbolic":"reference","module":"@angular/core","name":"ElementRef"}]}],"position":[{"__symbolic":"method"}],"activateNextItem":[{"__symbolic":"method"}],"activatePreviousItem":[{"__symbolic":"method"}],"resetScroll":[{"__symbolic":"method"}]}}}},{"__symbolic":"module","version":1,"metadata":{"MentionListComponent":{"__symbolic":"class","decorators":[{"__symbolic":"call","expression":{"__symbolic":"reference","module":"@angular/core","name":"Component"},"arguments":[{"selector":"mention-list","styles":[".scrollable-menu {\n\t\t\tdisplay: block;\n\t\t\theight: auto;\n\t\t\tmax-height: 300px;\n\t\t\toverflow: auto;\n\t\t}","[hidden] {\n\t\t\tdisplay: none;\n\t\t}"],"template":"\n    <ul class=\"dropdown-menu scrollable-menu\" #list [hidden]=\"hidden\">\n\t\t\t\t<li *ngFor=\"let item of items; let i = index\" [class.active]=\"activeIndex==i\">\n\t\t\t\t\t\t<a class=\"text-primary\" (mousedown)=\"activeIndex=i;itemClick.emit();$event.preventDefault()\">\n\t\t\t\t\t\t\t<ng-template [ngTemplateOutlet]=\"listTemplate\" [ngOutletContext]=\"{'item': item}\"></ng-template>\n\t\t\t\t\t\t</a>\n        </li>\n    </ul>\n    "}]}],"members":{"list":[{"__symbolic":"property","decorators":[{"__symbolic":"call","expression":{"__symbolic":"reference","module":"@angular/core","name":"ViewChild"},"arguments":["list"]}]}],"itemClick":[{"__symbolic":"property","decorators":[{"__symbolic":"call","expression":{"__symbolic":"reference","module":"@angular/core","name":"Output"}}]}],"listTemplate":[{"__symbolic":"property","decorators":[{"__symbolic":"call","expression":{"__symbolic":"reference","module":"@angular/core","name":"Input"}}]}],"__ctor__":[{"__symbolic":"constructor","parameters":[{"__symbolic":"reference","module":"@angular/core","name":"ElementRef"}]}],"position":[{"__symbolic":"method"}],"activateNextItem":[{"__symbolic":"method"}],"activatePreviousItem":[{"__symbolic":"method"}],"resetScroll":[{"__symbolic":"method"}]}}}}]